timezones_for_regions/__init__.py
timezones_for_regions/timezones.py
timezones_for_regions-1.0.0.dist-info/LICENSE
timezones_for_regions-1.0.0.dist-info/METADATA
timezones_for_regions-1.0.0.dist-info/WHEEL
timezones_for_regions-1.0.0.dist-info/top_level.txt
timezones_for_regions-1.0.0.dist-info/RECORD
