Metadata-Version: 2.1
Name: timezones-for-regions
Version: 1.0.0
Summary: Timezone data for regions
Author: Julia Vaniushina
Author-email: vanushinaulia@gmail.com
Classifier: Programming Language :: Python :: 3
Classifier: License :: OSI Approved :: MIT License
Classifier: Operating System :: OS Independent
Requires-Python: >=3.6
License-File: LICENSE
